primerdesigner/__init__.py
primerdesigner/database.py
primerdesigner/interface.py
primerdesigner/primer_designer.py
primerdesigner/utils.py
primerdesigner/web.py
primer_set_designer-0.1.7.dist-info/METADATA
primer_set_designer-0.1.7.dist-info/WHEEL
primer_set_designer-0.1.7.dist-info/top_level.txt
primer_set_designer-0.1.7.dist-info/RECORD
