Metadata-Version: 2.1
Name: primer_set_designer
Version: 0.1.7
Summary: A pipeline for searching species specific primer sets at genome level
Author-email: He Wencong <hewc@shanghaitech.edu.cn>
Classifier: Programming Language :: Python :: 3
Classifier: Operating System :: POSIX :: Linux
Requires-Python: >=3.9
Requires-Dist: primer3-py >=0.6.1
Requires-Dist: biopython >=1.79
Requires-Dist: pyfaidx >=0.7.1
Requires-Dist: tabulate >=0.8.10
Requires-Dist: jsonlines >=3.1.0
Requires-Dist: ncbi-datasets-pylib >=15.7.0
